gramat/__init__.py
gramat/actions.py
gramat/errors.py
gramat/grammar.py
gramat/options.py
gramat/compiling/__init__.py
gramat/compiling/compiler.py
gramat/expressions/__init__.py
gramat/expressions/_alternation.py
gramat/expressions/_char_literal.py
gramat/expressions/_char_predicate.py
gramat/expressions/_char_range.py
gramat/expressions/_custom.py
gramat/expressions/_expression.py
gramat/expressions/_literal.py
gramat/expressions/_negation.py
gramat/expressions/_optional.py
gramat/expressions/_reference.py
gramat/expressions/_repetition.py
gramat/expressions/_rule.py
gramat/expressions/_sequence.py
gramat/expressions/_true.py
gramat/lexing/__init__.py
gramat/lexing/lexer.py
gramat/lexing/nodes.py
gramat/linking/__init__.py
gramat/linking/link_context.py
gramat/linking/linker.py
gramat/parsing/__init__.py
gramat/parsing/basic_parsers.py
gramat/parsing/location.py
gramat/parsing/parsers.py
gramat/parsing/read_context.py
gramat/parsing/source.py
gramat/parsing/symbols.py
gramat/runtime/__init__.py
gramat-0.0.1.dist-info/METADATA
gramat-0.0.1.dist-info/WHEEL
gramat-0.0.1.dist-info/top_level.txt
gramat-0.0.1.dist-info/RECORD
