Metadata-Version: 2.1
Name: gramat
Version: 0.0.1
Summary: Gramat language implementation
Home-page: https://github.com/gramat-lang/python-gramat
Author: Sergio Pedraza
Author-email: sergio.uriel.ph@gmail.com
License: MIT
Platform: UNKNOWN
Classifier: Programming Language :: Python :: 3
Classifier: License :: OSI Approved :: MIT License
Classifier: Operating System :: OS Independent
Requires-Python: >=3.8
